[{"verseKey":"35:1","arabicIndopak":"اَلْحَمْدُ لِلّٰهِ فَاطِرِ السَّمٰوٰتِ وَالْاَرْضِ جَاعِلِ الْمَلٰ࢜ىِٕكَةِ رُسُلًا اُولِيْٓ اَجْنِحَةٍ مَّثْنٰي وَثُلٰثَ وَرُبٰعَؕ يَزِيْدُ فِي الْخَلْقِ مَا يَشَا࢜ءُؕ اِنَّ اللّٰهَ عَلٰي كُلِّ شَيْءٍ قَدِيْرٌ ۝١","transliterationEn":"Alhamdu lillaahi faatiris samaawaati wal-ardi jaa'ilil malaaa'ikati rusulan uleee ajnihatim masnaa Wa-sulaasa Wa-rubaa'; yazeedu fil khalqi maa yashaaa'; innal laaha 'alaa kulli shai'in Qadeer","translationBnTaisirul":"যাবতীয় প্রশংসা আকাশমন্ডলী ও পৃথিবীর সৃষ্টিকর্তা আল্লাহর জন্য। তিনি দূত মনোনীত করেন ফেরেশতামন্ডলীকে, যারা দুই দুই বা তিন তিন বা চার চার ডানা বিশিষ্ট। তিনি সৃষ্টিতে যা ইচ্ছে বৃদ্ধি করেন। আল্লাহ সকল বিষয়ের উপর সর্বশক্তিমান।"},{"verseKey":"35:2","arabicIndopak":"مَا يَفْتَحِ اللّٰهُ لِلنَّاسِ مِنْ رَّحْمَةٍ فَلَا مُمْسِكَ لَهَاۚ وَمَا يُمْسِكْۙ فَلَا مُرْسِلَ لَهٗ مِنْۢ بَعْدِهٖؕ وَهُوَ الْعَزِيْزُ الْحَكِيْمُ ۝٢","transliterationEn":"Maa yaftahil laahu linnaaasi mir rahmatin falaa mumsika lahaa Wa-maa yumsik falaa mursila lahoo mim ba'dihi; Wa-Huwal 'Azeezul Hakeem","translationBnTaisirul":"আল্লাহ মানুষের জন্য তাঁর অনুগ্রহ থেকে যা খুলে দেন তা নিবারণ করার কেউ নেই। আর তিনি যা বারিত করেন অতঃপর কেউ তা প্রেরণ করতে পারে না। তিনি মহাপরাক্রমশালী, মহাপ্রজ্ঞাময়।"},{"verseKey":"35:3","arabicIndopak":"يٰٓاَيُّهَا النَّاسُ اذْكُرُوْا نِعْمَتَ اللّٰهِ عَلَيْكُمْؕ هَلْ مِنْ خَالِقٍ غَيْرُ اللّٰهِ يَرْزُقُكُمْ مِّنَ السَّمَا࢜ءِ وَالْاَرْضِؕ لَا͏ٓ اِلٰهَ اِلَّا هُوَؗۖ فَاَنّٰي تُو͏ٔ͏ْفَكُوْنَ ۝٣","transliterationEn":"Yaaa-ayyuhan naasuzkuroo ni'matal laahi 'alaikum; hal min khaaliqin ghairul laahi yarzuqukum minas samaaa'i wal ard; laaa ilaaha illaa Huwa fa-annaa tu'fakoon","translationBnTaisirul":"হে মানুষ! তোমরা তোমাদের প্রতি আল্লাহর অনুগ্রহের কথা স্মরণ কর। তিনি ছাড়া কোন সৃষ্টিকর্তা আছে কি যে তোমাদেরকে আকাশ ও যমীন থেকে রিযক দান করে? তিনি ছাড়া সত্যিকারের কোন ইলাহ নেই, তাহলে কীভাবে তোমরা বিপথগামী হচ্ছ?"},{"verseKey":"35:4","arabicIndopak":"وَاِنْ يُّكَذِّبُوْكَ فَقَدْ كُذِّبَتْ رُسُلٌ مِّنْ قَبْلِكَؕ وَاِلَي اللّٰهِ تُرْجَعُ الْاُمُوْرُ ۝٤","transliterationEn":"Wa-ien yukazzibooka faqad kuzzibat Rusulum min qablik; Wa-ilal laahi turja'ul umoor","translationBnTaisirul":"তারা যদি তোমাকে মিথ্যে বলে অস্বীকার করে, তাহলে (তাদের এ আচরণ তো কোন নতুন বিষয় নয়) তোমার পূর্বেও রসূলদেরকে মিথ্যে বলে অস্বীকার করা হয়েছে। (যে যা-ই কিছু করুক না কেন) সমস্ত কার্যকলাপ (হিসাব নিকাশের জন্য) আল্লাহর কাছে ফিরে যাবে।"},{"verseKey":"35:5","arabicIndopak":"يٰٓاَيُّهَا النَّاسُ اِنَّ وَعْدَ اللّٰهِ حَقٌّ فَلَا تَغُرَّنَّكُمُ الْحَيٰوةُ الدُّنْيَاࣟ وَلَا يَغُرَّنَّكُمْ بِاللّٰهِ الْغَرُوْرُ ۝٥","transliterationEn":"Yaaa-ayyuhan naasu inna wa'dal laahi haqqun falaa taghurrannakumul hayaatud dunyaa; Wa-laa yaghurran-nakum billaahil gharoor","translationBnTaisirul":"হে মানুষ! আল্লাহর ওয়া‘দা সত্য, কাজেই পার্থিব জীবন কিছুতেই যেন তোমাদেরকে প্রতারিত না করে; আর সেই প্রধান প্রতারক (শয়ত্বান) যেন কিছুতেই তোমাদেরকে আল্লাহ সম্পর্কে প্রতারিত না করে।"},{"verseKey":"35:6","arabicIndopak":"اِنَّ الشَّيْطٰنَ لَكُمْ عَدُوٌّ فَاتَّخِذُوْهُ عَدُوًّاؕ اِنَّمَا يَدْعُوْا حِزْبَهٗ لِيَكُوْنُوْا مِنْ اَصْحٰبِ السَّعِيْرِ ۝٦ؕ","transliterationEn":"Innash shaitaana lakum 'aduwwun fattakhizoohu 'aduwwaa; innamaa yad'oo hizbahoo liyakoonoo min ashaabis sa'eer","translationBnTaisirul":"শয়ত্বান তোমাদের শত্রু, কাজেই তাকে শত্রু হিসেবে গ্রহণ কর। সে কেবল তার দলবলকে ডাকে, যাতে তারা জ্বলন্ত অগ্নির সঙ্গী হয়।"},{"verseKey":"35:7","arabicIndopak":"اَلَّذِيْنَ كَفَرُوْا لَهُمْ عَذَابٌ شَدِيْدٌ࣢ؕ وَالَّذِيْنَ اٰمَنُوْا وَعَمِلُوا الصّٰلِحٰتِ لَهُمْ مَّغْفِرَةٌ وَّاَجْرٌ كَبِيْرٌ ۝٧ࣖ","transliterationEn":"Allazeena kafaroo lahum 'azaabun shadeed; wallazeena aamanoo Wa-'amilus saalihaati lahum maghfiratunw Wa-ajrun kabeer","translationBnTaisirul":"যারা কুফুরী করে তাদের জন্য রয়েছে কঠিন শাস্তি। আর যারা ঈমান আনে আর সৎকাজ করে তাদের জন্য রয়েছে ক্ষমা ও মহা প্রতিফল।"},{"verseKey":"35:8","arabicIndopak":"اَفَمَنْ زُيِّنَ لَهٗ سُوْ࢜ءُ عَمَلِهٖ فَرَاٰهُ حَسَنًاؕ فَاِنَّ اللّٰهَ يُضِلُّ مَنْ يَّشَا࢜ءُ وَيَهْدِيْ مَنْ يَّشَا࢜ءُؗۖ فَلَا تَذْهَبْ نَفْسُكَ عَلَيْهِمْ حَسَرٰتٍؕ اِنَّ اللّٰهَ عَلِيْمٌۢ بِمَا يَصْنَعُوْنَ ۝٨","transliterationEn":"Afaman zuyyina lahoo sooo'u 'amalihee fara-aahu hasanaa; fa-innal laaha yudillu mai yashaaa'u Wa-yahdee mai yashaaa'u falaa tazhab nafsuka 'alaihim hasaraat; innal laaha 'aleemun bimaa yasna'oon","translationBnTaisirul":"যাকে তার মন্দ কর্ম শোভনীয় ক’রে দেখানো হয়, অতঃপর সে সেটাকে উত্তম মনে করে (সে কি তার সমান, যে সৎ পথে পরিচালিত?) আল্লাহ যাকে ইচ্ছে বিপথগামী করেন, আর যাকে ইচ্ছে সঠিক পথে পরিচালিত করেন। কাজেই তাদের জন্য আক্ষেপ ক’রে, তুমি তোমার জীবনকে ধ্বংস হতে দিও না। তারা যা করে আল্লাহ তা খুব ভালভাবেই জানেন।"},{"verseKey":"35:9","arabicIndopak":"وَاللّٰهُ الَّذِيْٓ اَرْسَلَ الرِّيٰحَ فَتُثِيْرُ سَحَابًا فَسُقْنٰهُ اِلٰي بَلَدٍ مَّيِّتٍ فَاَحْيَيْنَا بِهِ الْاَرْضَ بَعْدَ مَوْتِهَاؕ كَذٰلِكَ النُّشُوْرُ ۝٩","transliterationEn":"Wallaahul lazeee arsalar riyaaha fatuseeru sa-haaban fasuqnaahu ilaa baladim maiyitin fa-ahyaynaa bihil arda ba'da mawtihaa; kazaalikan nushoor","translationBnTaisirul":"আল্লাহ, যিনি বায়ু প্রেরণ করেন, অতঃপর তা মেঘ সঞ্চার করে, অতঃপর আমি তা নির্জীব ভূখন্ডের দিকে পরিচালিত করি। অতঃপর আমি তা দিয়ে মৃত্তিকাকে তার মৃত্যুর পর আবার সঞ্জীবিত করি। এভাবেই (ঘটবে) পুনরুত্থান।"},{"verseKey":"35:10","arabicIndopak":"مَنْ كَانَ يُرِيْدُ الْعِزَّةَ فَلِلّٰهِ الْعِزَّةُ جَمِيْعًاؕ اِلَيْهِ يَصْعَدُ الْكَلِمُ الطَّيِّبُ وَالْعَمَلُ الصَّالِحُ يَرْفَعُهٗؕ وَالَّذِيْنَ يَمْكُرُوْنَ السَّيِّاٰتِ لَهُمْ عَذَابٌ شَدِيْدٌؕ وَمَكْرُ اُولٰ࢜ىِٕكَ هُوَ يَبُوْرُ ۝١٠","transliterationEn":"Man kaana yureedul 'izzata falillaahil 'izzatu jamee'aa; ilaihi yas'adul kalimut taiyibu wal'amalus saalihu yarfa'uh; wallazeena yamkuroonas sayyiaati lahum 'azaabun shadeed; Wa-makru ulaaa'ika huwa yaboor","translationBnTaisirul":"কেউ সম্মান-সুখ্যাতি চাইলে (আল্লাহকে উপেক্ষা করে তা লাভ করা যাবে না), সে জেনে নিক যাবতীয় সম্মান-সুখ্যাতির অধিকারী হলেন আল্লাহ। তাঁরই দিকে উত্থিত হয় পবিত্র কথাগুলো আর সৎকাজ সেগুলোকে উচ্চে তুলে ধরে। যারা মন্দ কাজের চক্রান্ত করে তাদের জন্য আছে কঠিন শাস্তি। তাদের চক্রান্ত নিষ্ফল হবে।"},{"verseKey":"35:11","arabicIndopak":"وَاللّٰهُ خَلَقَكُمْ مِّنْ تُرَابٍ ثُمَّ مِنْ نُّطْفَةٍ ثُمَّ جَعَلَكُمْ اَزْوَاجًاؕ وَمَا تَحْمِلُ مِنْ اُنْثٰي وَلَا تَضَعُ اِلَّا بِعِلْمِهٖؕ وَمَا يُعَمَّرُ مِنْ مُّعَمَّرٍ وَّلَا يُنْقَصُ مِنْ عُمُرِهٖٓ اِلَّا فِيْ كِتٰبٍؕ اِنَّ ذٰلِكَ عَلَي اللّٰهِ يَسِيْرٌ ۝١١","transliterationEn":"Wallaahu khalaqakum min turaabin summa min nutfatin summa ja'alakum azwaajaa; Wa-maa tahmilu min unsaa Wa-laa tada'u illaa bi'ilmih; Wa-maa yu'ammaru mim mu'ammarinw Wa-laa yunqasu min 'umuriheee illaa fee kitaab; inna zaalika 'alal laahi yaseer","translationBnTaisirul":"আল্লাহ তোমাদেরকে মাটি থেকে সৃষ্টি করেছেন, অতঃপর শুক্র-বিন্দু হতে, অতঃপর তিনি তোমাদেরকে করেছেন (স্বামী-স্ত্রীর) জোড়া। তাঁর অবগতি ব্যতীত কোন নারী গর্ভ ধারণ করে না বা (তার বোঝা) হালকা করে না। কোন দীর্ঘায়ুর আয়ু দীর্ঘ করা হয় না, আর তার আয়ু কমানো হয় না কিতাবের লিখন ছাড়া। এটা (অর্থাৎ এ সবের হিসাব রাখা ও তত্ত্বাবধান করা) আল্লাহর জন্য সহজ।"},{"verseKey":"35:12","arabicIndopak":"وَمَا يَسْتَوِي الْبَحْرٰنِࣗۖ هٰذَا عَذْبٌ فُرَاتٌ سَا࢜ىِٕغٌ شَرَابُهٗ وَهٰذَا مِلْحٌ اُجَاجٌؕ وَمِنْ كُلٍّ تَاْكُلُوْنَ لَحْمًا طَرِيًّا وَّتَسْتَخْرِجُوْنَ حِلْيَةً تَلْبَسُوْنَهَاۚ وَتَرَي الْفُلْكَ فِيْهِ مَوَاخِرَ لِتَبْتَغُوْا مِنْ فَضْلِهٖ وَلَعَلَّكُمْ تَشْكُرُوْنَ ۝١٢","transliterationEn":"Wa-maa yastawil bahraani haaza 'azbun furaatun saaa'ighun sharaabuhoo Wa-haazaa milhun ujaaj; Wa-min kullin ta'kuloona lahman tariyyanw Wa-tastakhrijoona hilyatan talbasoonahaa Wa-taral fulka feehi mawaakhira litabtaghoo min fadlihee Wa-la'allakum tashkuroon","translationBnTaisirul":"দু’টি দরিয়াও এক রকম নয়। একটি সুমিষ্ট, সুস্বাদু, সুপেয়; অন্যটি লবণাক্ত, বিস্বাদ। তথাপি তোমরা সকল (প্রকার পানি) থেকে তাজা গোশত আহার কর আর বের কর অলংকার- পরিধান করার জন্যে। তোমরা দেখতে পাও নৌযানগুলো ঢেউয়ের বুক চিরে চলাচল করে যাতে তোমরা তাঁর অনুগ্রহ খোঁজ করতে পার, আর যাতে তোমরা কৃতজ্ঞতা প্রকাশ কর।"},{"verseKey":"35:13","arabicIndopak":"يُوْلِجُ الَّيْلَ فِي النَّهَارِ وَيُوْلِجُ النَّهَارَ فِي الَّيْلِۙ وَسَخَّرَ الشَّمْسَ وَالْقَمَرَؗۖ كُلٌّ يَّجْرِيْ لِاَجَلٍ مُّسَمًّيؕ ذٰلِكُمُ اللّٰهُ رَبُّكُمْ لَهُ الْمُلْكُؕ وَالَّذِيْنَ تَدْعُوْنَ مِنْ دُوْنِهٖ مَا يَمْلِكُوْنَ مِنْ قِطْمِيْرٍ ۝١٣ؕ","transliterationEn":"Yoolijul laila fin nahaari Wa-yoolijun nahaara fil laili Wa-sakhkharash shamsa wal-qamara kulluien yajree li-ajalim musammaa; zaalikumul laahu Rabbukum lahul mulk; wallazeena tad'oona min doonihee maa yamlikoona min qitmeer","translationBnTaisirul":"তিনি রাতকে দিনে ঢুকিয়ে দেন, আর দিনকে রাতে ঢুকিয়ে দেন। তিনি সূর্য ও চন্দ্রকে তাঁর নিয়ন্ত্রণের অধীনে (কাজে নিয়োজিত) রেখেছেন। প্রত্যেকেই নির্ধারিত সময় অনুসারে গতিশীল আছে। এই হলেন আল্লাহ, তোমাদের প্রতিপালক। রাজত্ব তাঁরই। তোমরা তাঁর পরিবর্তে যাদেরকে ডাক তারা তো খেজুরের অাঁটি সংলগ্ন (অত্যন্ত পাতলা ও দুর্বল) আবরণেরও মালিক নয়।"},{"verseKey":"35:14","arabicIndopak":"اِنْ تَدْعُوْهُمْ لَا يَسْمَعُوْا دُعَا࢜ءَكُمْۚ وَلَوْ سَمِعُوْا مَا اسْتَجَابُوْا لَكُمْؕ وَيَوْمَ الْقِيٰمَةِ يَكْفُرُوْنَ بِشِرْكِكُمْؕ وَلَا يُنَبِّي͏ٔ͏ُكَ مِثْلُ خَبِيْرٍ ۝١٤ࣖ","transliterationEn":"In tad'oohum laa yasma'oo du'aaa'akum Wa-law sami'oo mas tajaaboo lakum; Wa-Yawmal Qiyaamati Yakfuroona bishirkikum; Wa-laa yunabbi'uka mislu khabeer","translationBnTaisirul":"তোমরা তাদেরকে ডাকলে তারা তোমাদের ডাক শুনবে না আর যদি শুনেও, তবুও তোমাদের (ডাকে) সাড়া দিতে পারবে না। আর তোমরা যে তাদেরকে (আল্লাহর) অংশীদার গণ্য করতে, ক্বিয়ামতের দিন তা তারা অস্বীকার করবে। কেউই তোমাদেরকে সর্বজ্ঞ আল্লাহর মত খবর জানাতে পারবে না।"},{"verseKey":"35:15","arabicIndopak":"يٰٓاَيُّهَا النَّاسُ اَنْتُمُ الْفُقَرَا࢜ءُ اِلَي اللّٰهِۚ وَاللّٰهُ هُوَ الْغَنِيُّ الْحَمِيْدُ ۝١٥","transliterationEn":"Yaaa-ayyunhan naasu antumul fuqaraaa'u ilal laahi wallaahu Huwal Ghaniyyul Hameed","translationBnTaisirul":"হে মানুষ! তোমরাই আল্লাহর মুখাপেক্ষী, আর আল্লাহ তিনি তো অভাবহীন, প্রশংসিত।"},{"verseKey":"35:16","arabicIndopak":"اِنْ يَّشَاْ يُذْهِبْكُمْ وَيَاْتِ بِخَلْقٍ جَدِيْدٍ ۝١٦ۚ","transliterationEn":"Ien yasha' yuzhibkum Wa-ya'ti bikhalqin jadeed","translationBnTaisirul":"তিনি ইচ্ছে করলে তোমাদেরকে বিলুপ্ত করতে পারেন, আর এক নতুন সৃষ্টি আনতে পারেন।"},{"verseKey":"35:17","arabicIndopak":"وَمَا ذٰلِكَ عَلَي اللّٰهِ بِعَزِيْزٍ ۝١٧","transliterationEn":"Wa-maa zaalika 'alal laahi bi'azeez","translationBnTaisirul":"এটা আল্লাহর পক্ষে কঠিন নয়।"},{"verseKey":"35:18","arabicIndopak":"وَلَا تَزِرُ وَازِرَةٌ وِّزْرَ اُخْرٰيؕ وَاِنْ تَدْعُ مُثْقَلَةٌ اِلٰي حِمْلِهَا لَا يُحْمَلْ مِنْهُ شَيْءٌ وَّلَوْ كَانَ ذَا قُرْبٰيؕ اِنَّمَا تُنْذِرُ الَّذِيْنَ يَخْشَوْنَ رَبَّهُمْ بِالْغَيْبِ وَاَقَامُوا الصَّلٰوةَؕ وَمَنْ تَزَكّٰي فَاِنَّمَا يَتَزَكّٰي لِنَفْسِهٖؕ وَاِلَي اللّٰهِ الْمَصِيْرُ ۝١٨","transliterationEn":"Wa-laa taziru waaziratun wizra ukhraa; Wa-in tad'u musqalatun ilaa himlihaa laa yuhmal minhu shai'unw Wa-law kaana zaa qurbaa; innamaa tunzirul lazeena yakhshawna Rabbahum bilghaibi Wa-aqaamus Salaah; Wa-man tazakkaa fa-innamaa yatazakkaa linafsih; Wa-ilal laahil maseer","translationBnTaisirul":"কোন বহনকারী অন্যের (পাপের) বোঝা বইবে না। কেউ যদি তার গুরুভার বয়ে দেয়ার জন্য অন্যকে ডাকে তবে তার কিছুই বয়ে দেয়া হবে না- নিকটাত্মীয় হলেও। তুমি কেবল তাদেরকেই সতর্ক করতে পার, যারা না দেখেই তাদের প্রতিপালককে ভয় করে আর নামায প্রতিষ্ঠা করে। যে কেউ নিজেকে পরিশুদ্ধ করে সে তো পরিশুদ্ধ করে নিজের কল্যাণেই। আল্লাহর দিকেই (সকলের) প্রত্যাবর্তন।"},{"verseKey":"35:19","arabicIndopak":"وَمَا يَسْتَوِي الْاَعْمٰي وَالْبَصِيْرُ ۝١٩ۙ","transliterationEn":"Wa-maa yastawil a'maa wal-baseer","translationBnTaisirul":"অন্ধ আর চোখওয়ালা সমান নয়।"},{"verseKey":"35:20","arabicIndopak":"وَلَا الظُّلُمٰتُ وَلَا النُّوْرُ ۝٢٠ۙ","transliterationEn":"Wa-laz zulumaatu Wa-lan noor","translationBnTaisirul":"আর অন্ধকার ও আলোও (সমান নয়)।"},{"verseKey":"35:21","arabicIndopak":"وَلَا الظِّلُّ وَلَا الْحَرُوْرُ ۝٢١ۚ","transliterationEn":"Wa-laz zillu Wa-lal haroor","translationBnTaisirul":"আর ছায়া ও রোদও (সমান নয়)।"},{"verseKey":"35:22","arabicIndopak":"وَمَا يَسْتَوِي الْاَحْيَا࢜ءُ وَلَا الْاَمْوَاتُؕ اِنَّ اللّٰهَ يُسْمِعُ مَنْ يَّشَا࢜ءُۚ وَمَا͏ٓ اَنْتَ بِمُسْمِعٍ مَّنْ فِي الْقُبُوْرِ ۝٢٢","transliterationEn":"Wa-maa yastawil ahyaaa'u Wa-lal amwaat; innal laaha yusmi'u maien yashaaa'u Wa-maaa anta bi-musmi'im man fil quboor","translationBnTaisirul":"আর জীবিত ও মৃতও সমান নয়। আল্লাহ যাকে ইচ্ছে করেন শোনান; যারা ক্ববরে আছে তুমি তাদেরকে শোনাতে পার না।"},{"verseKey":"35:23","arabicIndopak":"اِنْ اَنْتَ اِلَّا نَذِيْرٌ ۝٢٣","transliterationEn":"In anta illaa nazeer","translationBnTaisirul":"তুমি তো কেবল একজন সতর্ককারী।"},{"verseKey":"35:24","arabicIndopak":"اِنَّا͏ٓ اَرْسَلْنٰكَ بِالْحَقِّ بَشِيْرًا وَّنَذِيْرًاؕ وَاِنْ مِّنْ اُمَّةٍ اِلَّا خَلَا فِيْهَا نَذِيْرٌ ۝٢٤","transliterationEn":"Innaa arsalnaaka bil-haqqi basheeranw Wa-nazeeraa; Wa-im min ummatin illaa khalaa feehaa nazeer","translationBnTaisirul":"আমি তোমাকে সত্যসহ পাঠিয়েছি সুসংবাদদাতা ও সতর্ককারীরূপে। এমন কোন সম্প্রদায় নেই যাতে সতর্ককারী আসেনি।"},{"verseKey":"35:25","arabicIndopak":"وَاِنْ يُّكَذِّبُوْكَ فَقَدْ كَذَّبَ الَّذِيْنَ مِنْ قَبْلِهِمْۚ جَا࢜ءَتْهُمْ رُسُلُهُمْ بِالْبَيِّنٰتِ وَبِالزُّبُرِ وَبِالْكِتٰبِ الْمُنِيْرِ ۝٢٥","transliterationEn":"Wa-ien yukazzibooka faqad kazzabal lazeena min qablihim jaaa'at-hum Rusuluhum bilbaiyyinaati Wa-biz-Zuburi Wa-bil-Kitaabil Muneer","translationBnTaisirul":"তারা যদি তোমাকে মিথ্যে ব’লে অস্বীকার করে, (তাহলে জেনে রেখ, এটা কোন নতুন ব্যাপার নয়, কারণ) তাদের পূর্ববর্তীরাও (নবী-রসূলদেরকে) মিথ্যে ব’লে অস্বীকার করেছিল। তাদের কাছে তাদের রসূলগণ সুস্পষ্ট নিদর্শন, লিখিত দলীল ও আলোকপ্রদ কিতাব নিয়ে এসেছিল।"},{"verseKey":"35:26","arabicIndopak":"ثُمَّ اَخَذْتُ الَّذِيْنَ كَفَرُوْا فَكَيْفَ كَانَ نَكِيْرِ ۝٢٦ࣖ","transliterationEn":"Summa akhaztul lazeena kafaroo fakaifa kaana nakeer","translationBnTaisirul":"যারা কুফরী করেছিল, অতঃপর আমি তাদেরকে পাকড়াও করেছিলাম। কী (ভয়ংকর) ছিল আমার শাস্তি!"},{"verseKey":"35:27","arabicIndopak":"اَلَمْ تَرَ اَنَّ اللّٰهَ اَنْزَلَ مِنَ السَّمَا࢜ءِ مَا࢜ءًۚ فَاَخْرَجْنَا بِهٖ ثَمَرٰتٍ مُّخْتَلِفًا اَلْوَانُهَاؕ وَمِنَ الْجِبَالِ جُدَدٌۢ بِيْضٌ وَّحُمْرٌ مُّخْتَلِفٌ اَلْوَانُهَا وَغَرَابِيْبُ سُوْدٌ ۝٢٧","transliterationEn":"Alam tara annal laaha anzala minas samaaa'i maaa'an fa-akhrajnaa bihee samaraatim mukhtalifan alwaanuhaa; Wa-minal jibaali judadum beedunw Wa-humrum mukhtalifun alwaanuhaa Wa-gharaabeebu sood","translationBnTaisirul":"তুমি কি দেখ না যে, আল্লাহ আকাশ হতে পানি বর্ষণ করেন, অতঃপর আমি তা দিয়ে রং বেরংয়ের ফলমূল উদগত করি। পাহাড়ের মধ্যে আছে বিভিন্ন বর্ণের গিরিপথ- সাদা, লাল আর নিকষ কালো।"},{"verseKey":"35:28","arabicIndopak":"وَمِنَ النَّاسِ وَالدَّوَا࢜بِّ وَالْاَنْعَامِ مُخْتَلِفٌ اَلْوَانُهٗ كَذٰلِكَؕ اِنَّمَا يَخْشَي اللّٰهَ مِنْ عِبَادِهِ الْعُلَمٰ࢜و͏ٔ͏ُاؕ اِنَّ اللّٰهَ عَزِيْزٌ غَفُوْرٌ ۝٢٨","transliterationEn":"Wa-minan naasi wadda-waaabbi wal-an'aami mukhtalifun alwaanuhoo kazalik; innamaa yakhshal laaha min 'ibaadihil 'ulamaaa'; innal laaha 'Azeezun Ghafoor","translationBnTaisirul":"তেমনিভাবে মানুষ, জীব-জন্তু আর গৃহপালিত পশুদের মধ্যেও রয়েছে তাদের বিভিন্ন রং। আল্লাহর বান্দাহদের মধ্যে তারাই তাঁকে ভয় করে যারা জ্ঞানী। আল্লাহ মহা ক্ষমতাশালী, পরম দয়ালু।"},{"verseKey":"35:29","arabicIndopak":"اِنَّ الَّذِيْنَ يَتْلُوْنَ كِتٰبَ اللّٰهِ وَاَقَامُوا الصَّلٰوةَ وَاَنْفَقُوْا مِمَّا رَزَقْنٰهُمْ سِرًّا وَّعَلَانِيَةً يَّرْجُوْنَ تِجَارَةً لَّنْ تَبُوْرَ ۝٢٩ۙ","transliterationEn":"Innal lazeena yatloona Kitabbal laahi Wa-aqaamus Salaata Wa-anfaqoo mimmaa razaqnaahum sirranw Wa-'alaa-niyataien yarjoona tijaaratal lan taboor","translationBnTaisirul":"যারা আল্লাহর কিতাব তিলাওয়াত করে, নামায প্রতিষ্ঠা করে আর আল্লাহ তাদেরকে যে রিযক দিয়েছেন তাথেকে গোপনে ও প্রকাশ্যে ব্যয় করে, তারা এমন এক ব্যবসায়ের আশা করে যাতে কক্ষনো লোকসান হবে না।"},{"verseKey":"35:30","arabicIndopak":"لِيُوَفِّيَهُمْ اُجُوْرَهُمْ وَيَزِيْدَهُمْ مِّنْ فَضْلِهٖؕ اِنَّهٗ غَفُوْرٌ شَكُوْرٌ ۝٣٠","transliterationEn":"Liyuwaffiyahum ujoorahum Wa-yazeedahum min fadlih; innahoo Ghafoorun Shakoor","translationBnTaisirul":"কারণ, তিনি তাদেরকে তাদের প্রতিফল পূর্ণমাত্রায় দান করবেন এবং নিজ অনুগ্রহে আরো বেশি দিবেন। তিনি অতি ক্ষমাশীল, (ভাল কাজের) বড়ই মর্যাদাদানকারী।"},{"verseKey":"35:31","arabicIndopak":"وَالَّذِيْٓ اَوْحَيْنَا͏ٓ اِلَيْكَ مِنَ الْكِتٰبِ هُوَ الْحَقُّ مُصَدِّقًا لِّمَا بَيْنَ يَدَيْهِؕ اِنَّ اللّٰهَ بِعِبَادِهٖ لَخَبِيْرٌۢ بَصِيْرٌ ۝٣١","transliterationEn":"Wallazeee awhainaaa ilaika minal Kitaabi huwal haqqu musaddiqal limaa baina yadayh; innal laaha bi'ibaadihee la-khabeerum Baseer","translationBnTaisirul":"আমি যে কিতাবটি হতে তোমার প্রতি ওয়াহী করেছি তা সত্য, পূর্ববর্তী কিতাবের সত্যায়নকারী। আল্লাহ তাঁর বান্দাহদের সম্পর্কে অবশ্যই সব খবর রাখেন এবং সব দেখেন।"},{"verseKey":"35:32","arabicIndopak":"ثُمَّ اَوْرَثْنَا الْكِتٰبَ الَّذِيْنَ اصْطَفَيْنَا مِنْ عِبَادِنَاۚ فَمِنْهُمْ ظَالِمٌ لِّنَفْسِهٖۚ وَمِنْهُمْ مُّقْتَصِدٌۚ وَمِنْهُمْ سَابِقٌۢ بِالْخَيْرٰتِ بِاِذْنِ اللّٰهِؕ ذٰلِكَ هُوَ الْفَضْلُ الْكَبِيْرُ ۝٣٢ؕ","transliterationEn":"Summa awrasnal Kitaabal lazeenas tafainaa min 'ibaadinaa faminhum zaalimul linafsihee Wa-minhum muqtasidu, Wa-minhum saabiqum bilkhairaati bi-iznil laah; zaalika huwal fadlul kabeer","translationBnTaisirul":"অতঃপর সেই কিতাবটির উত্তরাধিকারী করেছি আমি আমার বান্দাহদের মধ্যে হতে যাদেরকে বেছে নিয়েছি। অতঃপর তাদের কতক নিজেদের প্রতি অত্যাচার করেছে, আর কতক মধ্যপন্থী। তাদের কতক আল্লাহর নির্দেশে সৎ কাজে অগ্রণী। এটাই (মানুষের প্রতি আল্লাহর) খুবই বড় দয়া।"},{"verseKey":"35:33","arabicIndopak":"جَنّٰتُ عَدْنٍ يَّدْخُلُوْنَهَا يُحَلَّوْنَ فِيْهَا مِنْ اَسَاوِرَ مِنْ ذَهَبٍ وَّلُو͏ٔ͏ْلُو͏ٔ͏ًاۚ وَلِبَاسُهُمْ فِيْهَا حَرِيْرٌ ۝٣٣","transliterationEn":"Jannaatu 'adnien yad-khuloonahaa yuhallawna feeha min asaawira min zahabinw Wa-lu'lu'anw Wa-libaa-suhum feehaa hareer","translationBnTaisirul":"স্থায়ী জান্নাতে তারা প্রবেশ করবে। যেখানে তাদেরকে স্বর্ণ ও মুক্তার কঙ্কণে অলঙ্কৃত করা হবে। যেখানে তাদের পোশাক হবে রেশমের।"},{"verseKey":"35:34","arabicIndopak":"وَقَالُوا الْحَمْدُ لِلّٰهِ الَّذِيْٓ اَذْهَبَ عَنَّا الْحَزَنَؕ اِنَّ رَبَّنَا لَغَفُوْرٌ شَكُوْرُ ۝٣٤ۙ","transliterationEn":"Wa-qaalul hamdu lillaahil lazeee azhaba 'annal hazan; inna Rabbanaa la-Ghafoorun Shakoor","translationBnTaisirul":"আর তারা বলবে- যাবতীয় প্রশংসা আল্লাহর যিনি আমাদের দুঃখ কষ্ট দূর করে দিয়েছেন। আমাদের প্রতিপালক অবশ্যই পরম ক্ষমাশীল, (ভাল কাজের) বড়ই মর্যাদাদানকারী।"},{"verseKey":"35:35","arabicIndopak":"اࣙلَّذِيْٓ اَحَلَّنَا دَارَ الْمُقَامَةِ مِنْ فَضْلِهٖۚ لَا يَمَسُّنَا فِيْهَا نَصَبٌ وَّلَا يَمَسُّنَا فِيْهَا لُغُوْبٌ ۝٣٥","transliterationEn":"Allazeee ahallanaa daaral muqaamati min fadlihee laa yamassunaa feehaa nasabunw Wa-laa yamassunaa feehaa lughoob","translationBnTaisirul":"যিনি স্বীয় অনুগ্রহে আমাদেরকে স্থায়ী আবাস দান করেছেন। সেখানে ক্লেশ আমাদেরকে স্পর্শ করে না, ক্লান্তিও আমাদেরকে স্পর্শ করে না।"},{"verseKey":"35:36","arabicIndopak":"وَالَّذِيْنَ كَفَرُوْا لَهُمْ نَارُ جَهَنَّمَۚ لَا يُقْضٰي عَلَيْهِمْ فَيَمُوْتُوْا وَلَا يُخَفَّفُ عَنْهُمْ مِّنْ عَذَابِهَاؕ كَذٰلِكَ نَجْزِيْ كُلَّ كَفُوْرٍ ۝٣٦ۚ","transliterationEn":"Wallazeena kafaroo lahum naaru Jahannama laa yuqdaa 'alaihim fa-yamootoo Wa-laa yukhaffafu 'anhum min 'azaabihaa; kazaalika najzee kulla kafoor","translationBnTaisirul":"আর যারা কুফুরী করে, তাদের জন্য আছে জাহান্নামের আগুন। তাদের জন্য কোন সময় নির্ধারণ করা হবে না যে, তারা (নির্ধারিত সময় আসলে) মরে যাবে, আর তাদের থেকে শাস্তিও কমানো হবে না। প্রত্যেক অকৃতজ্ঞকে আমি এভাবেই প্রতিফল দিয়ে থাকি।"},{"verseKey":"35:37","arabicIndopak":"وَهُمْ يَصْطَرِخُوْنَ فِيْهَاۚ رَبَّنَا͏ٓ اَخْرِجْنَا نَعْمَلْ صَالِحًا غَيْرَ الَّذِيْ كُنَّا نَعْمَلُؕ اَوَلَمْ نُعَمِّرْكُمْ مَّا يَتَذَكَّرُ فِيْهِ مَنْ تَذَكَّرَ وَجَا࢜ءَكُمُ النَّذِيْرُؕ فَذُوْقُوْا فَمَا لِلظّٰلِمِيْنَ مِنْ نَّصِيْرٍ ۝٣٧ࣖ","transliterationEn":"Wa-hum yastarikhoona feehaa Rabbanaa akhrijnaa na'mal saalihan ghairal lazee kunnaa na'mal; awa-lamnu 'ammirkum maa yatazak-karu feehi man tazakkara Wa-jaaa'akumun nazeeru fazooqoo famaa lizzaalimeena min naseer","translationBnTaisirul":"সেখানে তারা চিৎকার করে বলবে- হে আমাদের পালনকর্তা! বের করুন আমাদেরকে, আমরা সৎকাজ করব, আমরা যে কাজ করতাম তা করব না। আমি কি তোমাদেরকে এতটা বয়স দেইনি যে, তখন কেউ নসীহত গ্রহণ করতে চাইলে নসীহত গ্রহণ করতে পারতে? আর তোমাদের কাছে সতর্ককারীও এসেছিল। কাজেই শাস্তি ভোগ কর, যালিমদের কোন সাহায্যকারী নেই।"},{"verseKey":"35:38","arabicIndopak":"اِنَّ اللّٰهَ عٰلِمُ غَيْبِ السَّمٰوٰتِ وَالْاَرْضِؕ اِنَّهٗ عَلِيْمٌۢ بِذَاتِ الصُّدُوْرِ ۝٣٨","transliterationEn":"Innal laaha 'aalimu ghaibis samaawaati wal-ard; innahoo 'aleemum bizaatis sudoor","translationBnTaisirul":"আল্লাহ আসমান যমীনের অদৃশ্য বিষয় সম্পর্কে অবগত। অন্তরে যা আছে সে সম্পর্কে তিনি বিশেষভাবে জ্ঞাত।"},{"verseKey":"35:39","arabicIndopak":"هُوَ الَّذِيْ جَعَلَكُمْ خَلٰ࢜ىِٕفَ فِي الْاَرْضِؕ فَمَنْ كَفَرَ فَعَلَيْهِ كُفْرُهٗؕ وَلَا يَزِيْدُ الْكٰفِرِيْنَ كُفْرُهُمْ عِنْدَ رَبِّهِمْ اِلَّا مَقْتًاۚ وَلَا يَزِيْدُ الْكٰفِرِيْنَ كُفْرُهُمْ اِلَّا خَسَارًا ۝٣٩","transliterationEn":"Huwal lazee ja'alakum khalaaa'ifa fil ard; faman kafara fa'alaihi kufruhoo; Wa-laa yazeedul kaafireena kufruhum 'inda Rabbihim illaa maqtanw Wa-laa yazeedul kaafireena kufruhum illaa khasaaraa","translationBnTaisirul":"তিনি তোমাদেরকে পৃথিবীতে (নিজের) প্রতিনিধি করেছেন। অতএব যে কুফুরী করবে তার কুফুরীর জন্য সে নিজেই দায়ী হবে। কাফিরদের কুফর তাদের প্রতিপালকের ঘৃণাই বৃদ্ধি করে। কাফিরদের কুফর তাদের ক্ষতিই বৃদ্ধি করে।"},{"verseKey":"35:40","arabicIndopak":"قُلْ اَرَءَيْتُمْ شُرَكَا࢜ءَكُمُ الَّذِيْنَ تَدْعُوْنَ مِنْ دُوْنِ اللّٰهِؕ اَرُوْنِيْ مَاذَا خَلَقُوْا مِنَ الْاَرْضِ اَمْ لَهُمْ شِرْكٌ فِي السَّمٰوٰتِۚ اَمْ اٰتَيْنٰهُمْ كِتٰبًا فَهُمْ عَلٰي بَيِّنَتٍ مِّنْهُۚ بَلْ اِنْ يَّعِدُ الظّٰلِمُوْنَ بَعْضُهُمْ بَعْضًا اِلَّا غُرُوْرًا ۝٤٠","transliterationEn":"Qul ara'aytum shurakaaa'a-kumul lazeena tad'oona min doonil laahi; aroonee maazaa khalaqoo minal ardi am lahum shirkun fis samaawaati am aatainaahum Kitaaban fahum 'alaa baiyyinatim minh; bal ien ya'iduz zaalimoona ba-'duhum ba'dan illaa ghurooraa","translationBnTaisirul":"বল- তোমরা কি তোমাদের শরীকদেরকে দেখেছ আল্লাহর পরিবর্তে তোমরা যাদেরকে ডেকে থাক? তারা পৃথিবীতে কী সৃষ্টি করেছে তা আমাকে দেখাও; কিংবা আকাশমন্ডলীতে তাদের কোন শরীকানা আছে কি? কিংবা আমি কি তাদেরকে কোন কিতাব দিয়েছি যাত্থেকে কোন সুস্পষ্ট প্রমাণের উপর তারা আছে? বরং সীমালঙ্ঘনকারীরা একে অপরকে প্রতারণামূলক ওয়া‘দা দিয়ে থাকে।"},{"verseKey":"35:41","arabicIndopak":"اِنَّ اللّٰهَ يُمْسِكُ السَّمٰوٰتِ وَالْاَرْضَ اَنْ تَزُوْلَا࣢ۚ وَلَىِٕنْ زَالَتَا͏ٓ اِنْ اَمْسَكَهُمَا مِنْ اَحَدٍ مِّنْۢ بَعْدِهٖؕ اِنَّهٗ كَانَ حَلِيْمًا غَفُوْرًا ۝٤١","transliterationEn":"Innal laaha yumsikus samaawaati wal-arda an tazoolaaa; Wa-la'in zaalataaa in amsa-kahumaa min ahadim mim ba'dih; innahoo kaana Haleeman Ghafooraa","translationBnTaisirul":"আল্লাহই আসমান ও যমীনকে স্থির রাখেন যাতে ও দু’টো টলে না যায়। ও দু’টো যদি টলে যায় তাহলে তিনি ছাড়া কে ও দু’টোকে স্থির রাখবে? তিনি পরম সহিষ্ণু, পরম ক্ষমাশীল।"},{"verseKey":"35:42","arabicIndopak":"وَاَقْسَمُوْا بِاللّٰهِ جَهْدَ اَيْمَانِهِمْ لَىِٕنْ جَا࢜ءَهُمْ نَذِيْرٌ لَّيَكُوْنُنَّ اَهْدٰي مِنْ اِحْدَي الْاُمَمِۚ فَلَمَّا جَا࢜ءَهُمْ نَذِيْرٌ مَّا زَادَهُمْ اِلَّا نُفُوْرَا ۝٤٢ۙ","transliterationEn":"Wa-aqsamoo billaahi jahda aymaanihim la'in jaaa'ahum nazeerul layakoonunna ahdaa min ihdal umami falam-maa jaaa'ahum nazeerum maa zaadahum illaa nufooraa","translationBnTaisirul":"আর তারা (অর্থাৎ মক্কার মুশরিকরা) শক্তভাবে কসম খেয়ে বলত যে, তাদের কাছে সতর্ককারী আসলে তারা অন্য যে কোন সম্প্রদায়ের চেয়ে অবশ্য অবশ্যই সৎ পথের অধিক অনুসারী হয়ে যাবে। কিন্তু তাদের কাছে যখন সতর্ককারী আসল, তা বাড়িয়েই তুলল তাদের ঘৃণা,"},{"verseKey":"35:43","arabicIndopak":"اࣙسْتِكْبَارًا فِي الْاَرْضِ وَمَكْرَ السَّيِّىءِؕ وَلَا يَحِيْقُ الْمَكْرُ السَّيِّي͏ٔ͏ُ اِلَّا بِاَهْلِهٖؕ فَهَلْ يَنْظُرُوْنَ اِلَّا سُنَّتَ الْاَوَّلِيْنَۚ فَلَنْ تَجِدَ لِسُنَّتِ اللّٰهِ تَبْدِيْلًا࣢ۚ وَلَنْ تَجِدَ لِسُنَّتِ اللّٰهِ تَحْوِيْلًا ۝٤٣","transliterationEn":"Istikbaaran fil ardi Wa-makras sayyi'; Wa-laa yaheequl makrus sayyi'u illaa bi-ahlih; fahal yanzuroona illaa sunnatal awwaleen; falan tajida lisunnatil laahi tabdeelanw Wa-lan tajida lisunnatil laahi tahweela","translationBnTaisirul":"যমীনে উদ্ধত আচরণ আর কু-চক্রান্ত। কু-চক্রান্ত তাকেই ঘিরে ধরবে যে তা করবে। তাহলে তারা কি তাদের পূর্ববর্তীদের উপর (আল্লাহর পক্ষ হতে) যে বিধান প্রয়োগ করা হয়েছে তারই অপেক্ষা করছে? তুমি আল্লাহর বিধানে কক্ষনো কোন পরিবর্তন পাবে না। তুমি আল্লাহর বিধানে কক্ষনো কোন ব্যতিক্রম পাবে না।"},{"verseKey":"35:44","arabicIndopak":"اَوَلَمْ يَسِيْرُوْا فِي الْاَرْضِ فَيَنْظُرُوْا كَيْفَ كَانَ عَاقِبَةُ الَّذِيْنَ مِنْ قَبْلِهِمْ وَكَانُوْٓا اَشَدَّ مِنْهُمْ قُوَّةًؕ وَمَا كَانَ اللّٰهُ لِيُعْجِزَهٗ مِنْ شَيْءٍ فِي السَّمٰوٰتِ وَلَا فِي الْاَرْضِؕ اِنَّهٗ كَانَ عَلِيْمًا قَدِيْرًا ۝٤٤","transliterationEn":"Awalam yaseeroo fil ardi fa-yanzuroo kaifa kaana 'aaqibatul lazeena min Qablihim Wa-kaanoo ashadda minhum quwwah; Wa-maa kaanal laahu liyu'jizahoo min shai'in fis samaawaati Wa-laa fil ard; innahoo kaana 'Aleeman Qadeeraa","translationBnTaisirul":"তারা কি পৃথিবীতে ভ্রমণ করে না? তাহলে দেখত, তাদের পূর্ববর্তীদের পরিণাম কী হয়েছিল। তারা তো শক্তিতে ছিল এদের চেয়েও শক্তিশালী। আসমান ও যমীনের কোন কিছুই আল্লাহকে অপারগ করতে পারে না। তিনি সর্বজ্ঞাতা, সকল শক্তির অধিকারী।"},{"verseKey":"35:45","arabicIndopak":"وَلَوْ يُو͏ٔ͏َاخِذُ اللّٰهُ النَّاسَ بِمَا كَسَبُوْا مَا تَرَكَ عَلٰي ظَهْرِهَا مِنْ دَا࢜بَّةٍ وَّلٰكِنْ يُّو͏ٔ͏َخِّرُهُمْ اِلٰٓي اَجَلٍ مُّسَمًّيۚ فَاِذَا جَا࢜ءَ اَجَلُهُمْ فَاِنَّ اللّٰهَ كَانَ بِعِبَادِهٖ بَصِيْرًا ۝٤٥ࣖ","transliterationEn":"Wa-law yu'aakhizul laahun naasa bima kasaboo maa taraka 'alaa zahrihaa min daaabbatinw Wa-laakiny yu'akhkhiruhum ilaaa ajalim musamman fa-izaa jaaa'a ajaluhum fa-innal laaha kaana bi'ibaadihee Baseeraa","translationBnTaisirul":"আল্লাহ মানুষকে তার কৃতকর্মের জন্য পাকড়াও করতে চাইলে ভূপৃষ্ঠের একটি প্রাণীকেও রেহাই দিতেন না। কিন্তু তিনি তাদের জন্য একটা নির্ধারিত কাল পর্যন্ত সময় বিলম্বিত করেন। অতঃপর তাদের সে নির্ধারিত সময় যখন এসে যায়, (তখন আল্লাহর ফয়সালা কার্যকরী হতে এক মুহূর্তও বিলম্ব ঘটে না), কারণ আল্লাহ (প্রতিটি মুহূর্তে) তাঁর বান্দাহদের পর্যবেক্ষণকারী।"}]
